encrawler/__init__.py
encrawler/models/__init__.py
encrawler/models/result.py
encrawler/spiders/__init__.py
encrawler/spiders/basic_search_engine_spider.py
encrawler/spiders/bing.py
encrawler/spiders/sm.py
encrawler/utils/__init__.py
encrawler/utils/proxies.py
Encrawler-0.1.20.dist-info/LICENSE
Encrawler-0.1.20.dist-info/METADATA
Encrawler-0.1.20.dist-info/WHEEL
Encrawler-0.1.20.dist-info/top_level.txt
Encrawler-0.1.20.dist-info/RECORD
