Metadata-Version: 2.1
Name: Encrawler
Version: 0.1.20
Summary: update module import
Author: phimes
Author-email: phimes@163.com
License-File: LICENSE
